ocean_provider/__init__.py
ocean_provider/config.py
ocean_provider/constants.py
ocean_provider/exceptions.py
ocean_provider/log.py
ocean_provider/myapp.py
ocean_provider/routes.py
ocean_provider/run.py
ocean_provider/user_nonce.py
ocean_provider/util.py
ocean_provider/utils/__init__.py
ocean_provider/utils/accounts.py
ocean_provider/utils/basics.py
ocean_provider/utils/encryption.py
ocean_provider/utils/web3.py
ocean_provider-0.4.0.dist-info/LICENSE
ocean_provider-0.4.0.dist-info/METADATA
ocean_provider-0.4.0.dist-info/WHEEL
ocean_provider-0.4.0.dist-info/top_level.txt
ocean_provider-0.4.0.dist-info/RECORD
