Metadata-Version: 2.1
Name: ocean-provider
Version: 0.4.0
Summary: 🐳 Ocean Provider.
Home-page: https://github.com/oceanprotocol/provider-py
Author: leucothia
Author-email: devops@oceanprotocol.com
License: Apache Software License 2.0
Keywords: ocean-provider
Platform: UNKNOWN
Classifier: Development Status :: 2 - Pre-Alpha
Classifier: Intended Audience :: Developers
Classifier: License :: OSI Approved :: Apache Software License
Classifier: Natural Language :: English
Classifier: Programming Language :: Python :: 3.6
Requires-Dist: Flask (==1.1.2)
Requires-Dist: Flask-Cors (==3.0.8)
Requires-Dist: Flask-RESTful (==0.3.8)
Requires-Dist: flask-swagger (==0.2.14)
Requires-Dist: flask-swagger-ui (==3.25.0)
Requires-Dist: Jinja2 (>=2.10.1)
Requires-Dist: gunicorn (==20.0.4)
Requires-Dist: osmosis-azure-driver (==0.1.0)
Requires-Dist: osmosis-aws-driver (==0.1.0)
Requires-Dist: osmosis-driver-interface (==0.1.0)
Requires-Dist: osmosis-on-premise-driver (==0.1.0)
Requires-Dist: osmosis-ipfs-driver (==0.1.0)
Requires-Dist: Werkzeug (>=0.15.3)
Requires-Dist: ocean-lib (>=0.5.0)
Requires-Dist: requests-testadapter
Requires-Dist: eciespy
Provides-Extra: dev
Requires-Dist: bumpversion ; extra == 'dev'
Requires-Dist: pkginfo ; extra == 'dev'
Requires-Dist: twine ; extra == 'dev'
Requires-Dist: watchdog ; extra == 'dev'
Requires-Dist: codacy-coverage ; extra == 'dev'
Requires-Dist: coverage ; extra == 'dev'
Requires-Dist: docker ; extra == 'dev'
Requires-Dist: mccabe ; extra == 'dev'
Requires-Dist: pylint ; extra == 'dev'
Requires-Dist: pytest ; extra == 'dev'
Requires-Dist: pytest-watch ; extra == 'dev'
Requires-Dist: tox ; extra == 'dev'
Requires-Dist: plecos ; extra == 'dev'
Provides-Extra: test
Requires-Dist: codacy-coverage ; extra == 'test'
Requires-Dist: coverage ; extra == 'test'
Requires-Dist: docker ; extra == 'test'
Requires-Dist: mccabe ; extra == 'test'
Requires-Dist: pylint ; extra == 'test'
Requires-Dist: pytest ; extra == 'test'
Requires-Dist: pytest-watch ; extra == 'test'
Requires-Dist: tox ; extra == 'test'
Requires-Dist: plecos ; extra == 'test'
